textlang/__init__.py
textlang/functional.py
textlang/lang_detect.py
textlang-0.0.1.dist-info/METADATA
textlang-0.0.1.dist-info/WHEEL
textlang-0.0.1.dist-info/top_level.txt
textlang-0.0.1.dist-info/RECORD
